CHANGES.txt
MANIFEST.in
README.txt
setup.py
pyindexcrawler/__init__.py
pyindexcrawler.egg-info/PKG-INFO
pyindexcrawler.egg-info/SOURCES.txt
pyindexcrawler.egg-info/dependency_links.txt
pyindexcrawler.egg-info/requires.txt
pyindexcrawler.egg-info/top_level.txt