Metadata-Version: 1.0
Name: pyindexcrawler
Version: 0.1.0
Summary: Artifactory file structure crawler
Home-page: https://testpypi.python.org/pypi
Author: Anthony
Author-email: ACTrevis@rockwellautomation.com
License: UNKNOWN
Platform: UNKNOWN
